spatula/__init__.py
spatula/cli.py
spatula/config.py
spatula/pages.py
spatula/py.typed
spatula/selectors.py
spatula/sources.py
spatula/utils.py
spatula-0.9.1.dist-info/LICENSE
spatula-0.9.1.dist-info/METADATA
spatula-0.9.1.dist-info/WHEEL
spatula-0.9.1.dist-info/entry_points.txt
spatula-0.9.1.dist-info/RECORD
