Metadata-Version: 2.1
Name: spatula
Version: 0.9.1
Summary: A modern Python library for writing maintainable web scrapers.
Home-page: https://github.com/jamesturk/spatula/
License: MIT
Author: James Turk
Author-email: dev@jamesturk.net
Requires-Python: >=3.8,<4.0
Classifier: Intended Audience :: Developers
Classifier: License :: OSI Approved :: MIT License
Classifier: Natural Language :: English
Classifier: Operating System :: OS Independent
Classifier: Programming Language :: Python :: 3
Classifier: Programming Language :: Python :: 3.8
Classifier: Programming Language :: Python :: 3.9
Classifier: Programming Language :: Python :: 3.10
Classifier: Programming Language :: Python :: 3.11
Classifier: Programming Language :: Python :: 3.12
Classifier: Topic :: Software Development :: Libraries :: Python Modules
Requires-Dist: attrs[attrs] (>=20.3.0,<21.0.0)
Requires-Dist: click (>=8,<9)
Requires-Dist: cssselect (>=1.1.0,<2.0.0)
Requires-Dist: ipython[shell] (>=7.19.0,<8.0.0)
Requires-Dist: lxml (>4.6,<6)
Requires-Dist: openpyxl (>=3.0.6,<4.0.0)
Requires-Dist: scrapelib (>=2.0.6,<3.0.0)
Project-URL: Documentation, https://jamesturk.github.io/spatula/
Project-URL: Repository, https://github.com/jamesturk/spatula/
